tidygraphtool/__init__.py
tidygraphtool/all.py
tidygraphtool/as_data_frame.py
tidygraphtool/augment.py
tidygraphtool/centrality.py
tidygraphtool/cli.py
tidygraphtool/context.py
tidygraphtool/edgedataframe.py
tidygraphtool/graph_measures.py
tidygraphtool/group.py
tidygraphtool/gt_graph.py
tidygraphtool/networkx.py
tidygraphtool/node.py
tidygraphtool/nodedataframe.py
tidygraphtool/pipes.py
tidygraphtool/play.py
tidygraphtool/state.py
tidygraphtool/utils.py
tidygraphtool/verbs.py
tidygraphtool/verbs_dataframe.py
tidygraphtool-0.2.1.dist-info/LICENSE
tidygraphtool-0.2.1.dist-info/METADATA
tidygraphtool-0.2.1.dist-info/WHEEL
tidygraphtool-0.2.1.dist-info/top_level.txt
tidygraphtool-0.2.1.dist-info/RECORD
