Metadata-Version: 2.1
Name: tidygraphtool
Version: 0.2.1
Summary: A tidy API for network manipulation with Graph-tool inspired by tidygraph.
Home-page: https://github.com/jstonge/tidygraphtool
Author: Jonathan St-Onge
Author-email: jonathanstonge7@gmail.com
License: MIT
Platform: UNKNOWN
Classifier: Programming Language :: Python :: 3.6
Classifier: Programming Language :: Python :: 3.7
Classifier: License :: OSI Approved :: MIT License
Classifier: Operating System :: OS Independent
Requires-Python: >=3.6
License-File: LICENSE
